symspelljpy/__init__.py
symspelljpy/core.py
symspelljpy/path_resolver.py
symspelljpy/resources/spellcheckclient-jar-with-dependencies.jar
symspelljpy-0.4.dist-info/METADATA
symspelljpy-0.4.dist-info/WHEEL
symspelljpy-0.4.dist-info/top_level.txt
symspelljpy-0.4.dist-info/RECORD
