Metadata-Version: 2.1
Name: symspelljpy
Version: 0.4
Summary: Spelling Correction
Home-page: https://bitbucket.org/rbcmllab/spellchecker/symspelljpy/master
Author: Keyi Tang
Author-email: keyi.tang@rbc.com
License: UNKNOWN
Platform: UNKNOWN
Classifier: Programming Language :: Python :: 3
Classifier: License :: OSI Approved :: MIT License
Classifier: Operating System :: OS Independent
